yafowil.widget.datetime-1.14-py3.9-nspkg.pth
yafowil/widget/datetime/__init__.py
yafowil/widget/datetime/example.py
yafowil/widget/datetime/tests.py
yafowil/widget/datetime/widget.py
yafowil/widget/datetime/locales/yafowil.widget.datetime.pot
yafowil/widget/datetime/locales/de/LC_MESSAGES/yafowil.widget.datetime.mo
yafowil/widget/datetime/locales/de/LC_MESSAGES/yafowil.widget.datetime.po
yafowil/widget/datetime/locales/en/LC_MESSAGES/yafowil.widget.datetime.mo
yafowil/widget/datetime/locales/en/LC_MESSAGES/yafowil.widget.datetime.po
yafowil/widget/datetime/resources/jquery.ui.datepicker.bootstrap.css
yafowil/widget/datetime/resources/jquery.ui.datepicker.css
yafowil/widget/datetime/resources/jquery.ui.datepicker.js
yafowil/widget/datetime/resources/jquery.ui.datepicker.min.js
yafowil/widget/datetime/resources/jquery.ui.datepicker.plone5.css
yafowil/widget/datetime/resources/jquery.ui.timepicker.bootstrap.css
yafowil/widget/datetime/resources/jquery.ui.timepicker.css
yafowil/widget/datetime/resources/jquery.ui.timepicker.js
yafowil/widget/datetime/resources/jquery.ui.timepicker.plone5.css
yafowil/widget/datetime/resources/widget-bootstrap.css
yafowil/widget/datetime/resources/widget-plone5.css
yafowil/widget/datetime/resources/widget.css
yafowil/widget/datetime/resources/widget.js
yafowil_widget_datetime-1.14.dist-info/licenses/LICENSE.rst
yafowil_widget_datetime-1.14.dist-info/METADATA
yafowil_widget_datetime-1.14.dist-info/WHEEL
yafowil_widget_datetime-1.14.dist-info/entry_points.txt
yafowil_widget_datetime-1.14.dist-info/namespace_packages.txt
yafowil_widget_datetime-1.14.dist-info/top_level.txt
yafowil_widget_datetime-1.14.dist-info/RECORD
